fcast/GageUSGS.py
fcast/NHDPlusStreamSegment.py
fcast/NWM.py
fcast/__init__.py
fcast/plotting.py
fcast-0.1.0.dist-info/LICENSE
fcast-0.1.0.dist-info/METADATA
fcast-0.1.0.dist-info/WHEEL
fcast-0.1.0.dist-info/top_level.txt
fcast-0.1.0.dist-info/RECORD
