Metadata-Version: 2.1
Name: fcast
Version: 0.1.0
Summary: A collection of python tools used for forecasting flood events and their impact on transportation infrastructure.
Home-page: https://github.com/Dewberry/fcast
Author: Dewberry
Author-email: abrazeau@dewberry.com
License: Apache License 2.0
Platform: UNKNOWN
Classifier: License :: OSI Approved :: Apache Software License
Classifier: Programming Language :: Python :: 3
Classifier: Programming Language :: Python :: 3.7
Requires-Dist: gcsfs
Requires-Dist: xarray
Requires-Dist: matplotlib
Requires-Dist: numpy
Requires-Dist: pandas
Requires-Dist: scipy
Requires-Dist: boto3
Requires-Dist: requests
Requires-Dist: beautifulsoup4
Requires-Dist: fiona
Requires-Dist: shapely
